Workbook

Sheet Лифты
A1: 46284.444 | B1: 3 | C1: Екатерина 130 кв. | D1: Застряли в лифте | E1: Нет электричества в машинном отделении | F1: Сработал автомат в ВРУ во 2 подъезде на 1 этаже | G1: Включили автомат обратно | H1: 46284.462 | I1: Андрей электрик
A2: 46276.845 | B2: 2 | C2: Елнара 71 | D2: Девочки застряли в лифте | E2: Ошибка F44 | F2: Сработала защита. | G2: Вытащили девченок дочери Аракси и Эльнары. Переключили флажок тормоза на первом этаже | H2: 46276.893 | I2: Леха

Sheet Расходы
A1: 46266 | B1: 2000 | C1: Лехе за замену ремня 1 подъезде
A2: 46266 | B2: 12500 | C2: Услуги дворника
A3: 46265 | B3: 1850 | C3: Комиссия Т-инвестиции
A4: 46263 | B4: 358 | C4: 2 лампы и изолента
A5: 46259 | B5: 482 | C5: 2 светильника
A6: 46248 | B6: 1271.05 | C6: ЕМС в Госжилинспекцию
A7: 46248 | B7: 100 | C7: Конверт на почте
A8: 46247 | B8: 6000 | C8: Лехе и егг лругу за лифт в 3 подъезде
A9: 46231 | B9: 709.97 | C9: Кофе, Кружка, вафли
A10: 46231 | B10: 370 | C10: Картридж NS-CF283A
A11: 46231 | B11: 610 | C11: Бумага и папка
A12: 46230 | B12: 1152 | C12: Лехе на пиво
... A16: 46216 | B16: 1000 | C16: Володе сантехнику зс устранение засора
A17: 13.07.0206 | B17: 250 | C17: Ключ в подвал
A18: 46210 | B18: 178.9 | C18: Письмо в УК
A19: 46210 | B19: 50 | C19: Конверт для УК
A20: 46210 | B20: 910.74 | C20: Бандероль в ГЖИ
A21: 46209 | B21: 130 | C21: Пакет для бандероли в ГЖИ
A22: 46161 | B22: 437 | C22: Бумага
A23: 46157 | B23: 390 | C23: Бумага
A24: 46125 | B24: 386 | C24: Бумага
A25: 46125 | B25: 600 | C25: Картридж NS-CF283A
B26: 40222.57

Sheet Заявки
A1: 2607131225 | B1: 158 | C1: Анна | D1: Запах канализации в подъезде | F1: 2607131408 | G1: 1.5055556 | H1: 1.5055556 | I1: 1494.7167
A2: 2607100852 | B2: 158 | C2: Анна | D2: Не работает лифт 3 подъезд в 8:52 | F2: 2607112100 | G2: 1.5055556 | H2: 1.5055556 | I2: 9547.1333
A3: 2607090816 | B3: 44 | C3: Гульнур | D3: Не работает лифт 1 подъезд в 6:40 | F3: 2607131840

Sheet Письма
A1: 46282 | B1: УТВиВ | C1: 5-3
A2: 46272 | B2: УТВиВ | C2: 5-2
A3: 46272 | B3: Администрация | C3: 3-4
A4: 04.09.0226 | B4: Администрация | C4: 3-3
A5: 46268 | B5: Администрация | C5: 3-2
A6: 46265 | B6: Администрация | C6: 3-1
A7: 46265 | B7: УТВиВ | C7: 5-1
A8: 46261 | B8: ГЖИ | C8: 2-2
A9: 46227 | B9: ГЖИ | C9: 2-1
A10: 46209 | B10: Налоговая | C10: 1-1

Sheet Выполненые работы
A1: 46217 | B1: Замена тормозных колодок лифта 1 подъезда
A2: 46216 | B2: Регулировка тормозных колодок лифта 1 подъезда
A3: 46216 | B3: Прочистка северного стояка 3 подъезда
A4: 46214 | B4: Перезапуск лифта 1 подъезда. Выявлен дефект
A5: 46214 | B5: Перезапуск лифта 3 подъезда

Sheet Задачи1
A1: Договор с РКЦ
A2: Договор с УТВиВ | B2: Письмо в администрацию по актам
B3: Протокол разногласий
A4: Договор с ГЭТ

Sheet Лист1
A1: ДАШБОРД ТСН «СОЛНЕЧНЫЙ» | B1: (заголовок)
A2: =TODAY() -> 46284 | B2: Дата обновления
A4: БЛОК 1. ЗАДАЧИ
A5: =COUNTA(Задачи1!A:A)-1 -> 2 | B5: Всего задач
A6: A6 | B6: Просрочено | C6: =COUNTIFS(Задачи1!E:E,"<>Готово",Задачи1!D:D,"<"&TODAY()) -> 0
A7: A7 | B7: На сегодня | C7: =COUNTIF(Задачи1!D:D,TODAY()) -> 0
A8: A8 | B8: В работе | C8: =COUNTIF(Задачи1!E:E,"В работе") -> 0
A9: A9 | B9: Готово | C9: =COUNTIF(Задачи1!E:E,"Готово") -> 0
A10: A11 | B10: БЛОК 2. ПОДГОТОВКА К ЗИМЕ
A11: A12 | B11: Собрано документов | C11: =COUNTIF(Оценочный_лист!C:C,"Да") -> #REF!
A12: A13 | B12: Всего документов | C12: =COUNTA(Оценочный_лист!A:A)-1 -> #REF!
A13: A14 | B13: Процент готовности | C13: =A12/A13 (формат: процент) -> =A12/A13 (формат: процент)
A14: A16 | B14: БЛОК 3. ПЕРЕПИСКА
A15: A17 | B15: Входящих всего | C15: =COUNTA(Переписка!A:A)-1 -> #REF!
A16: A18 | B16: Ожидают ответа | C16: =COUNTIF(Переписка!F:F,"") -> #REF!
A17: A20 | B17: БЛОК 4. ФИНАНСЫ
A18: A21 | B18: Остаток на счёте | C18: (вводите вручную)
A19: A22 | B19: Задолженность жильцов | C19: =SUM(Финансы!C:C) -> #REF!
A20: A23 | B20: К оплате подрядчикам | C20: (вводите вручную)

Sheet Дашборд
A1: ДАШБОРД ТСН «СОЛНЕЧНЫЙ»
A2: =TODAY() -> 46284
A4: ЗАДАЧИ
A5: =COUNTA(Задачи!A:A)-1 -> 3
A6: =COUNTIFS(Задачи!E:E,"<>Готово",Задачи!D:D,"<"&TODAY()) -> 0
A7: =COUNTIF(Задачи!D:D,TODAY()) -> 2
A8: =COUNTIF(Задачи!E:E,"В работе") -> 1
A9: =COUNTIF(Задачи!E:E,"Готово") -> 1
A11: ПОДГОТОВКА К ЗИМЕ
A12: =COUNTIF('Оценочный лист'!C:C,"Да") -> 17
A13: =COUNTA('Оценочный лист'!A:A)-1 -> 21
A14: =A12/A13 -> 0.80952381
A16: ПЕРЕПИСКА
A17: =COUNTA(Переписка!A:A)-1 -> 2
A18: =COUNTIF(Переписка!F:F,"") -> 998
A20: ФИНАНСЫ
A22: =SUMIF(Финансы!D:D,"Задолженность",Финансы!C:C) -> -20000
A28: A18 | B28: Ожидают ответа
A29: A20 | C29: (текст)
A30: A21 | B30: Остаток на счёте | C30: (вводите вручную)
A31: A22 | B31: Задолженность жильцов
A32: A23 | B32: К оплате подрядчикам | C32: (вводите вручную)

Sheet Задачи
A1: № | B1: Задача | C1: Тип | D1: Срок | E1: Статус | F1: Ответственный | G1: Комментарий
A2: 1 | B2: Подписать акт с УТВиВ | C2: С | D2: 46284 | E2: В работе | F2: Я | G2: Ждём подпись
A3: 2 | B3: Заполнить оценочный лист | C3: В | D3: 46285 | E3: Не начато | F3: Я
A4: 3 | B4: Ответить жильцу по мусору | C4: Р | D4: 46284 | E4: Готово | F4: Я

Sheet Оценочный лист
A1: № | B1: Наименование документа | C1: Наличие (Да/Нет)
A2: 1.1.1 | B2: Акт промывки | C2: Да
A3: 1.1.2 | B3: Акт наладки режимов | C3: Да
A4: 1.1.3 | B4: Акт осмотра арматуры | C4: Да
A5: 1.1.4 | B5: Приказ о назначении ответственного | C5: Да
A6: 1.1.5 | B6: Акт гидравлических испытаний | C6: Да
A7: 1.1.6 | B7: Перечень инструкций для ОПО | C7: Да
A8: 1.1.7 | B8: Эксплуатационные инструкции | C8: Да
A9: 1.1.8 | B9: Паспорт теплового пункта | C9: Да
A10: 1.1.9 | B10: Штатное расписание / договоры | C10: Да
A11: 1.1.10 | B11: Проверка регуляторов | C11: Да
A12: 1.2.1 | B12: Акт осмотра на врезки | C12: Да
... A19: 2.2 | B19: Акт дезинфекции | C19: Нет
A20: 3 | B20: Газовое оборудование | C20: Да
A21: 4 | B21: Предписания | C21: Да
A22: 5 | B22: План подготовки | C22: Да

Sheet Переписка
A1: Вх. № | B1: Дата | C1: От кого | D1: Исх. № отпр. | E1: Кратко | F1: Исх. № | G1: Дата ответа
A2: 46086 | B2: 46282 | C2: УТВиВ | D2: 1088516 | E2: Договор СОИ | F2: 46117 | G2: 46283
A3: 46025 | B3: 46280 | C3: Администрация | D3: 123/45 | E3: Передача сетей

Sheet Финансы
A1: Дата | B1: Контрагент | C1: Сумма | D1: Тип (приход/расход)
A2: 46266 | B2: Жильцы | C2: 150000 | D2: Приход
A3: 46270 | B3: УТВиВ | C3: 45000 | D3: Расход
A4: 46275 | B4: Жильцы (долг) | C4: -20000 | D4: Задолженность
